bodge/__init__.py
bodge/common.py
bodge/hamiltonian.py
bodge/lattice.py
bodge-1.3.0.dist-info/licenses/LICENSE.md
bodge-1.3.0.dist-info/WHEEL
bodge-1.3.0.dist-info/METADATA
bodge-1.3.0.dist-info/RECORD
