Metadata-Version: 2.4
Name: bodge
Version: 1.3.0
Summary: Bodge: Python package for efficient tight-binding modeling of superconductors.
Author-email: Jabir Ali Ouassou <jabir.ali.ouassou@hvl.no>
Requires-Python: >=3.11
Classifier: License :: OSI Approved :: MIT License
License-File: LICENSE.md
Requires-Dist: beartype
Requires-Dist: numpy
Requires-Dist: scipy
Requires-Dist: black ; extra == "all"
Requires-Dist: cupy ; extra == "all"
Requires-Dist: flit ; extra == "all"
Requires-Dist: isort ; extra == "all"
Requires-Dist: pytest ; extra == "all"
Requires-Dist: pytest-cov ; extra == "all"
Requires-Dist: quarto ; extra == "all"
Requires-Dist: cupy ; extra == "cuda"
Requires-Dist: black ; extra == "dev"
Requires-Dist: flit ; extra == "dev"
Requires-Dist: isort ; extra == "dev"
Requires-Dist: pytest ; extra == "dev"
Requires-Dist: pytest-cov ; extra == "dev"
Requires-Dist: quarto ; extra == "dev"
Provides-Extra: all
Provides-Extra: cuda
Provides-Extra: dev
